qr3/__init__.py
qr3/qr.py
qr3-1.0.0.dist-info/METADATA
qr3-1.0.0.dist-info/RECORD
qr3-1.0.0.dist-info/WHEEL
qr3-1.0.0.dist-info/top_level.txt
test/__init__.py
test/test_qr3.py
