Metadata-Version: 2.1
Name: qr3
Version: 1.0.0
Summary: Redis-powered queues, capped collections, deques, and stacks
Home-page: http://github.com/doctorondemand/qr3
Author: Ted Nyman
Author-email: ted@ted.io
Maintainer: DoctorOnDemand
Maintainer-email: sustaining@doctorondemand.com
License: MIT
Keywords: Redis,queue,data structures
Platform: UNKNOWN
Classifier: Programming Language :: Python :: 2.7
Classifier: Programming Language :: Python :: 3.6
Classifier: Intended Audience :: Developers
Classifier: License :: OSI Approved :: MIT License
Classifier: Operating System :: OS Independent
Requires-Dist: future
Requires-Dist: redis
